setup.py
jd_py_base/__init__.py
jd_py_base/__version__.py
jd_py_base.egg-info/PKG-INFO
jd_py_base.egg-info/SOURCES.txt
jd_py_base.egg-info/dependency_links.txt
jd_py_base.egg-info/requires.txt
jd_py_base.egg-info/top_level.txt
jd_py_base/commons/__init__.py
jd_py_base/commons/common_fun.py
jd_py_base/monitor/__init__.py
jd_py_base/monitor/monitor_signal_alert.py
jd_py_base/request_downloader/__init__.py
jd_py_base/request_downloader/downloaders.py